[
    {
        "name": "argh",
        "github": "adishavit/argh",
        "branch": "master",
        "tag": "39b9a00046143f6b300dcf98ea989486cf62097d"
    },
    {
        "name": "glfw",
        "github": "glfw/glfw",
        "branch": "master",
        "tag": "6b57e08bb0078c9834889eab871bac2368198c15"
    },
    {
        "name": "gli",
        "github": "g-truc/gli",
        "branch": "master",
        "tag": "779b99ac6656e4d30c3b24e96e0136a59649a869"
    },
    {
        "name": "glm",
        "github": "g-truc/glm",
        "branch": "master",
        "tag": "cc98465e3508535ba8c7f6208df934c156a018dc"
    },
    {
        "name": "physfs",
        "github": "icculus/physfs",
        "branch": "main",
        "tag": "0d4e9aac4575744ddaae56b146f1be19f064f0e5"
    },
    {
        "name": "json",
        "github": "nlohmann/json",
        "branch": "develop",
        "tag": "307c053b9b250abc6e6d478a4336fd98592ae173"
    },
    {
        "name": "spdlog",
        "github": "gabime/spdlog",
        "branch": "v1.x",
        "tag": "f44fa31f5110331af196d0ed7f00ae1c7b8ef3cc"
    },
    {
        "name": "stb",
        "github": "nothings/stb",
        "branch": "master",
        "tag": "af1a5bc352164740c1cc1354942b1c6b72eacb8a"
    },
    {
        "name": "tinyobjloader",
        "github": "syoyo/tinyobjloader",
        "branch": "master",
        "tag": "a1e8bad32e1ccd26a7936c5354ecf856aec2cf59"
    },
    {
        "name": "Vulkan-Headers",
        "github": "KhronosGroup/Vulkan-Headers",
        "branch": "main",
        "tag": "9f4c61a31435a7a90a314fc68aeb386c92a09c0f"
    },
    {
        "name": "Vulkan-Profiles",
        "github": "KhronosGroup/Vulkan-Profiles",
        "branch": "master",
        "tag": "aa3c9e1e71134c27b40e2e3bd737d6ebba02ec2b"
    },
    {
        "name": "volk",
        "github": "zeux/volk",
        "branch": "master",
        "tag": "3872818bb956e3b1e3847f3ddbb467b181e6a864"
    },
    {
        "name": "VulkanMemoryAllocator",
        "github": "GPUOpen-LibrariesAndSDKs/VulkanMemoryAllocator",
        "branch": "master",
        "tag": "2a7110f07854d86ea6dbfddf58cea40d81f8be70"
    },
    {
        "name": "IconFontCppHeaders",
        "github": "juliettef/IconFontCppHeaders",
        "branch": "main",
        "tag": "7d6ff1f4ba51e7a2b142be39457768abece1549c"
    },
    {
        "name": "imgui",
        "github": "ocornut/imgui",
        "branch": "master",
        "tag": "5867a43dc8ee16e4c87572fd86a4b8c12c7deae5"
    },
    {
        "name": "imgui_docking",
        "github": "ocornut/imgui",
        "branch": "docking",
        "tag": "bc2002ab92f0eb6411fef32abd4037f449cf85a6"
    },
    {
        "name": "SPIRV-Headers",
        "github": "KhronosGroup/SPIRV-Headers",
        "branch": "master",
        "tag": "87d5b782bec60822aa878941e6b13c0a9a954c9b"
    },
    {
        "name": "SPIRV-Tools",
        "github": "KhronosGroup/SPIRV-Tools",
        "branch": "master",
        "tag": "4c456f7da67c5437a6fb7d4d20d78e2a5ae2acf2"
    },
    {
        "name": "glslang",
        "github": "KhronosGroup/glslang",
        "branch": "master",
        "tag": "69ae9e7460499b488cb2d32edae623a95264db14"
    },
    {
        "name": "shaderc",
        "github": "google/shaderc",
        "branch": "main",
        "tag": "31bddbb37ef1e974da7bce859ab59bcfc5ad9ee7"
    },
    {
        "name": "PicoSHA2",
        "github": "okdshin/PicoSHA2",
        "branch": "master",
        "tag": "27fcf6979298949e8a462e16d09a0351c18fcaf2"
    },
    {
        "name": "Catch2",
        "github": "catchorg/Catch2",
        "branch": "devel",
        "tag": "7b2e7d623b626ed2cae1d4b7f2b5480bdabbefd8"
    }
]
